src/ml/__init__.py
src/ml/tensor.py
reinforcement_learning-0.0.1.dist-info/METADATA
reinforcement_learning-0.0.1.dist-info/WHEEL
reinforcement_learning-0.0.1.dist-info/licenses/LICENSE
reinforcement_learning-0.0.1.dist-info/RECORD
